README.md
setup.cfg
setup.py
embod_client/__init__.py
embod_client/async_client.py
embod_client.egg-info/PKG-INFO
embod_client.egg-info/SOURCES.txt
embod_client.egg-info/dependency_links.txt
embod_client.egg-info/requires.txt
embod_client.egg-info/top_level.txt