Metadata-Version: 1.0
Name: embod-client
Version: 0.0.6
Summary: Client library for controlling agents in embod.ai environments
Home-page: https://github.com/embod/embod_client
Author: Chris Bamford
Author-email: chris.bamford@embod.ai
License: UNKNOWN
Keywords: embod,environment,agents
Platform: UNKNOWN
